{
  "ZDuyZbbsemaZ": [
    [
      "pt1",
      0.9885,
      1.0,
      443961.0,
      -5105.55149999998,
      0.0,
      -5105.55149999998,
      438855.4485,
      -0.011499999999999955,
      1243.0908000000109,
      0.0
    ]
  ],
  "cm": [
    [
      "t4",
      1.1077,
      1.05080981503226,
      0.0009999999991996411,
      5.6890184922207334e-05,
      3852.4612201098143,
      3852.4612769999994,
      0.0011076999991134423,
      0.05413937341838909,
      -0.005215999999563792,
      2.2756073968882936e-05
    ]
  ],
  "syj": [
    [
      "t4",
      1.1077,
      0,
      0.0,
      0.0,
      3803.741963999997,
      3803.741963999997,
      0.0,
      0.0,
      -107.33491200000299,
      0.0
    ],
    [
      "m3",
      1.0,
      1.0,
      37261.99,
      0.0,
      0.0,
      0.0,
      37261.99,
      0.0,
      0.0,
      0.0
    ]
  ],
  "hxy": [
    [
      "t4",
      1.1077,
      1.0,
      0.0009999999941792126,
      0.0001076999993731011,
      91604.44912230001,
      91604.44923000001,
      0.0011076999935523137,
      0.1076999999999999,
      -0.006079999991925433,
      5.384999968655055e-05
    ]
  ],
  "cl": [
    [
      "t4",
      1.1077,
      1.0,
      0.0009999999983847374,
      0.00010769999982603613,
      1996.0791152999986,
      1996.0792229999984,
      0.0011076999982107736,
      0.1076999999999999,
      -48.237984000001234,
      4.3079999930414455e-05
    ],
    [
      "m3",
      1.0,
      1.0,
      16746.12,
      0.0,
      0.0,
      0.0,
      16746.12,
      0.0,
      0.0,
      0.0
    ]
  ],
  "zb": [
    [
      "t4",
      1.1077,
      0,
      0.0,
      0.0,
      1551.9354599999986,
      1551.9354599999986,
      0.0,
      0.0,
      -46.11136000000124,
      0.0
    ],
    [
      "m3",
      1.0,
      1.0,
      16007.85,
      0.0,
      0.0,
      0.0,
      16007.85,
      0.0,
      0.0,
      0.0
    ]
  ],
  "zy": [
    [
      "t4",
      1.1077,
      0,
      0.0,
      0.0,
      620.6709659999998,
      620.6709659999998,
      0.0,
      0.0,
      -24.123968000000673,
      0.0
    ],
    [
      "m3",
      1.0,
      1.0,
      8374.79,
      0.0,
      0.0,
      0.0,
      8374.79,
      0.0,
      0.0,
      0.0
    ]
  ],
  "lbc": [
    [
      "t4",
      1.1077,
      0,
      0.0,
      0.0,
      3008.1918799999985,
      3008.1918799999985,
      0.0,
      0.0,
      -102.86208000000306,
      0.0
    ],
    [
      "m3",
      1.0,
      1.0,
      35709.21,
      0.0,
      0.0,
      0.0,
      35709.21,
      0.0,
      0.0,
      0.0
    ]
  ],
  "lz": [
    [
      "t4",
      1.1077,
      0,
      0.0,
      0.0,
      2721.3743699999973,
      2721.3743699999973,
      0.0,
      0.0,
      -80.85792000000265,
      0.0
    ],
    [
      "m3",
      1.0,
      1.0,
      28070.33,
      0.0,
      0.0,
      0.0,
      28070.33,
      0.0,
      0.0,
      0.0
    ]
  ],
  "house": [
    [
      "t4",
      1.1077,
      0,
      0.0,
      0.0,
      -20008.805390000012,
      -20008.805390000012,
      0.0,
      0.0,
      -197.00640000000567,
      0.0
    ],
    [
      "m3",
      1.0,
      1.0,
      68392.0,
      0.0,
      0.0,
      0.0,
      68392.0,
      0.0,
      0.0,
      0.0
    ]
  ],
  "lhx": [
    [
      "t4",
      1.1077,
      0,
      0.0,
      0.0,
      -4430.58548,
      -4430.58548,
      0.0,
      0.0,
      -16.089280000000144,
      0.0
    ],
    [
      "m3",
      1.0,
      1.0,
      5585.49,
      0.0,
      0.0,
      0.0,
      5585.49,
      0.0,
      0.0,
      0.0
    ]
  ],
  "sey": [
    [
      "t4",
      1.1077,
      0,
      0.0,
      0.0,
      -3259.68093,
      -3259.68093,
      0.0,
      0.0,
      -19.47168000000056,
      0.0
    ],
    [
      "m3",
      1.0,
      1.0,
      6759.72,
      0.0,
      0.0,
      0.0,
      6759.72,
      0.0,
      0.0,
      0.0
    ]
  ],
  "miao": [
    [
      "t4",
      1.1077,
      0,
      0.0,
      0.0,
      -17175.2868,
      -17175.2868,
      0.0,
      0.0,
      -94.82560000000012,
      0.0
    ],
    [
      "m3",
      1.0,
      1.0,
      32919.3,
      0.0,
      0.0,
      0.0,
      32919.3,
      0.0,
      0.0,
      0.0
    ]
  ],
  "hmk": [
    [
      "t4",
      1.1077,
      0,
      0.0,
      0.0,
      -892.6830000000002,
      -892.6830000000002,
      0.0,
      0.0,
      -6.096000000000117,
      0.0
    ],
    [
      "m3",
      1.0,
      1.0,
      2116.26,
      0.0,
      0.0,
      0.0,
      2116.26,
      0.0,
      0.0,
      0.0
    ]
  ]
}